ckanext_georchestra-0.2.1-py2.7-nspkg.pth
ckanext/georchestra/__init__.py
ckanext/georchestra/controller.py
ckanext/georchestra/plugin.py
ckanext/georchestra/commands/__init__.py
ckanext/georchestra/commands/georchestra_ldap.py
ckanext/georchestra/templates/organization/edit_base.html
ckanext/georchestra/templates/organization/index.html
ckanext/georchestra/templates/organization/snippets/organization_form.html
ckanext/georchestra/templates/organization/snippets/organization_item.html
ckanext/georchestra/templates/snippets/organization.html
ckanext/georchestra/templates/user/dashboard_organizations.html
ckanext/georchestra/templates/user/edit_user_form.html
ckanext/georchestra/tests/__init__.py
ckanext/georchestra/tests/test_georchestra.py
ckanext/georchestra/tests/test_plugin.py
ckanext/georchestra/tests/test_unittests_georchestra.py
ckanext/georchestra/utils/__init__.py
ckanext/georchestra/utils/ldap_utils.py
ckanext/georchestra/utils/organizations.py
ckanext/georchestra/utils/users.py
ckanext_georchestra-0.2.1.dist-info/LICENSE
ckanext_georchestra-0.2.1.dist-info/METADATA
ckanext_georchestra-0.2.1.dist-info/WHEEL
ckanext_georchestra-0.2.1.dist-info/entry_points.txt
ckanext_georchestra-0.2.1.dist-info/namespace_packages.txt
ckanext_georchestra-0.2.1.dist-info/top_level.txt
ckanext_georchestra-0.2.1.dist-info/RECORD
