Metadata-Version: 2.1
Name: ckanext-georchestra
Version: 0.2.1
Summary: CKAN integration in geOrchestra
Home-page: https://github.com/georchestra/ckanext-georchestra
Author: Jean Pommier
Author-email: jean.pommier@pi-geosolutions.fr
License: AGPL
Keywords: CKAN georchestra sso header LDAP
Platform: UNKNOWN
Classifier: Development Status :: 4 - Beta
Classifier: License :: OSI Approved :: GNU Affero General Public License v3 or later (AGPLv3+)
Classifier: Programming Language :: Python :: 2.7
